remotecv_redis/__init__.py
remotecv_redis/loader.py
tc_multidir/__init__.py
tc_multidir/_version.py
tc_multidir/loader.py
tc_multidir/loaders/__init__.py
tc_multidir/loaders/multidir_loader.py
thumbor_multidir-0.2.8.dist-info/LICENSE
thumbor_multidir-0.2.8.dist-info/METADATA
thumbor_multidir-0.2.8.dist-info/WHEEL
thumbor_multidir-0.2.8.dist-info/top_level.txt
thumbor_multidir-0.2.8.dist-info/RECORD
