Metadata-Version: 2.1
Name: thumbor-multidir
Version: 0.2.8
Summary: Thumbor file loader for multiple paths
Home-page: https://github.com/benneic/thumbor_multidir
Author: Benn Eichhorn
Author-email: beichhor@gmail.com
License: MIT
Keywords: imaging face detection feature thumbor file loader
Platform: UNKNOWN
Classifier: Development Status :: 5 - Production/Stable
Classifier: Intended Audience :: Developers
Classifier: License :: OSI Approved :: MIT License
Classifier: Natural Language :: English
Classifier: Operating System :: MacOS
Classifier: Operating System :: POSIX :: Linux
Classifier: Programming Language :: Python :: 2.7
Classifier: Topic :: Internet :: WWW/HTTP :: Dynamic Content
Classifier: Topic :: Multimedia :: Graphics :: Presentation
Requires-Dist: python-dateutil
Requires-Dist: six
Requires-Dist: thumbor (<7,>=6.0.0)
Provides-Extra: tests
Requires-Dist: mock (<3.0.0,>=1.0.1) ; extra == 'tests'
Requires-Dist: nose ; extra == 'tests'
Requires-Dist: nose-focus ; extra == 'tests'
Requires-Dist: colorama ; extra == 'tests'
Requires-Dist: numpy ; extra == 'tests'
Requires-Dist: flake8 ; extra == 'tests'
Requires-Dist: thumbor (<7.0.0) ; extra == 'tests'
Requires-Dist: preggy (>=1.3.0) ; extra == 'tests'
Requires-Dist: yanc (>=0.3.3) ; extra == 'tests'
